redis_mongo_postgres_read_user/__init__.py
redis_mongo_postgres_read_user/script.py
redis_mongo_postgres_create_read_user-0.1.1.dist-info/entry_points.txt
redis_mongo_postgres_create_read_user-0.1.1.dist-info/WHEEL
redis_mongo_postgres_create_read_user-0.1.1.dist-info/METADATA
redis_mongo_postgres_create_read_user-0.1.1.dist-info/RECORD
