Metadata-Version: 2.1
Name: redis-mongo-postgres-create-read-user
Version: 0.1.1
Summary: 
Author: ARJUN
Author-email: 74967141+arjun2038@users.noreply.github.com
Requires-Python: >=3.8,<4.0
Classifier: Programming Language :: Python :: 3
Classifier: Programming Language :: Python :: 3.8
Classifier: Programming Language :: Python :: 3.9
Classifier: Programming Language :: Python :: 3.10
Requires-Dist: psycopg2 (==2.9.3)
Requires-Dist: pymongo (==3.12.0)
Requires-Dist: redis (==4.3.4)
Requires-Dist: typer (==0.6.1)
